evcnet/__init__.py
evcnet-0.1.0.dist-info/WHEEL
evcnet-0.1.0.dist-info/METADATA
evcnet-0.1.0.dist-info/RECORD
